{
    "partname": "optimization",
    "runtime": 20.295188610441983,
    "results": {
        "CONF1": {
            "xtb_opt": {
                "energy": -399.3652401,
                "cycles": 3,
                "converged": true,
                "ecyc": [
                    -399.3651821,
                    -399.3652399,
                    -399.3652401
                ],
                "grad_norm": 0.000187531064,
                "gncyc": [
                    0.024189503157,
                    0.0078917,
                    0.0004145,
                    0.0001857,
                    0.000187531064
                ],
                "geom": [
                    {
                        "element": "S",
                        "xyz": [
                            -8.699133582659916e-09,
                            -0.06165339301528858,
                            2.28022460077703e-11
                        ]
                    },
                    {
                        "element": "H",
                        "xyz": [
                            -0.975703646951653,
                            0.8662646313402846,
                            1.2315012046712241e-08
                        ]
                    },
                    {
                        "element": "H",
                        "xyz": [
                            0.9756781470349133,
                            0.8662914645257273,
                            5.067983064307657e-10
                        ]
                    }
                ]
            },
            "xtb_rrho": {
                "energy": -0.005453850147,
                "rmsd": null,
                "gibbs": {
                    "298.15": -0.005453850147
                },
                "enthalpy": {
                    "298.15": null
                },
                "entropy": {
                    "298.15": null
                },
                "symmetry": "c1",
                "symnum": 1,
                "linear": false
            },
            "gtot": -399.370693950147,
            "bmw": 1.0
        }
    },
    "settings": {
        "optcycles": 8,
        "maxcyc": 200,
        "threshold": 1.5,
        "hlow": 0.01,
        "gradthr": 0.01,
        "func": "r2scan-3c",
        "basis": "def2-tzvp",
        "prog": "orca",
        "sm": "smd",
        "gfnv": "gfn2",
        "optlevel": "normal",
        "run": true,
        "macrocycles": false,
        "crestcheck": true,
        "template": false,
        "constrain": false,
        "xtb_opt": true
    },
    "nconf_in": 1,
    "nconf_out": 1
}