{
    "partname": "refinement",
    "runtime": 471.8133682254702,
    "results": {
        "CONF1": {
            "gsolv": {
                "gsolv": -0.0004750168739633409,
                "energy_gas": -350.208760482724,
                "energy_solv": -350.209235499598
            },
            "gtot": -350.209235499598,
            "bmw": 1.0
        }
    },
    "settings": {
        "threshold": 0.95,
        "func": "wb97x-v",
        "basis": "def2-tzvp",
        "prog": "orca",
        "sm": "smd",
        "gfnv": "gfn2",
        "run": true,
        "implicit": false,
        "template": false
    },
    "nconf_in": 1,
    "nconf_out": 1
}